regscale/__init__.py
regscale/_version.py
regscale/regscale.py
regscale/airflow/__init__.py
regscale/airflow/click_dags.py
regscale/airflow/click_mixins.py
regscale/airflow/config.py
regscale/airflow/hierarchy.py
regscale/airflow/azure/__init__.py
regscale/airflow/azure/cli.py
regscale/airflow/azure/upload_dags.py
regscale/airflow/factories/__init__.py
regscale/airflow/factories/connections.py
regscale/airflow/factories/workflows.py
regscale/airflow/operators/__init__.py
regscale/airflow/operators/click.py
regscale/airflow/sensors/__init__.py
regscale/airflow/sensors/sql.py
regscale/airflow/sessions/__init__.py
regscale/airflow/sessions/sql/__init__.py
regscale/airflow/sessions/sql/queries.py
regscale/airflow/sessions/sql/sql_server_queries.py
regscale/airflow/tasks/__init__.py
regscale/airflow/tasks/branches.py
regscale/airflow/tasks/cli.py
regscale/airflow/tasks/click.py
regscale/airflow/tasks/debugging.py
regscale/airflow/tasks/groups.py
regscale/airflow/tasks/init.py
regscale/airflow/tasks/states.py
regscale/airflow/tasks/workflows.py
regscale/ansible/__init__.py
regscale/core/__init__.py
regscale/core/decorators.py
regscale/core/lazy_group.py
regscale/core/login.py
regscale/core/app/__init__.py
regscale/core/app/api.py
regscale/core/app/application.py
regscale/core/app/config.py
regscale/core/app/config_defaults.py
regscale/core/app/logz.py
regscale/core/app/internal/__init__.py
regscale/core/app/internal/admin_actions.py
regscale/core/app/internal/assessments_editor.py
regscale/core/app/internal/catalog.py
regscale/core/app/internal/comparison.py
regscale/core/app/internal/control_editor.py
regscale/core/app/internal/encrypt.py
regscale/core/app/internal/evidence.py
regscale/core/app/internal/file_uploads.py
regscale/core/app/internal/healthcheck.py
regscale/core/app/internal/login.py
regscale/core/app/internal/migrations.py
regscale/core/app/internal/model_editor.py
regscale/core/app/internal/poam_editor.py
regscale/core/app/internal/set_permissions.py
regscale_cli-6.29.4.12.dist-info/LICENSE
regscale_cli-6.29.4.12.dist-info/METADATA
regscale_cli-6.29.4.12.dist-info/WHEEL
regscale_cli-6.29.4.12.dist-info/entry_points.txt
regscale_cli-6.29.4.12.dist-info/top_level.txt
regscale_cli-6.29.4.12.dist-info/RECORD
