Metadata-Version: 2.1
Name: regscale-cli
Version: 6.29.4.12
Summary: Command Line Interface (CLI) for bulk processing/loading data into RegScale
Home-page: https://github.com/RegScale/regscale-cli
Author: Travis Howerton
Author-email: thowerton@regscale.com
Maintainer: Shawn Therrien, Anthony Berlardo
Maintainer-email: stherrien@regscale.com, abelardo@regscale.com
License: MIT
Classifier: Operating System :: OS Independent
Classifier: Programming Language :: Python :: 3.10
Classifier: Programming Language :: Python :: 3.11
Classifier: Programming Language :: Python :: 3.12
Classifier: Programming Language :: Python :: 3.13
Requires-Python: >=3.10, <4
License-File: LICENSE
Requires-Dist: PyMuPDF >=1.24.7
Requires-Dist: PyYAML ==6.0.1
Requires-Dist: aiohttp
Requires-Dist: beautifulsoup4
Requires-Dist: boto3 ==1.35.10
Requires-Dist: botocore ==1.35.10
Requires-Dist: bs4
Requires-Dist: cacheout
Requires-Dist: click ~=8.1.8
Requires-Dist: colorama ==0.4.5
Requires-Dist: crowdstrike-falconpy ==1.4.5
Requires-Dist: cryptography ~=44.0.1
Requires-Dist: distro ==1.8.0
Requires-Dist: docx ==0.2.4
Requires-Dist: filelock ~=3.13.1
Requires-Dist: frontend
Requires-Dist: google-api-python-client
Requires-Dist: google-cloud-asset ~=3.22
Requires-Dist: google-cloud-securitycenter ~=1.25
Requires-Dist: gql ~=3.5.0
Requires-Dist: inflect
Requires-Dist: jira >=3.8.0
Requires-Dist: jwcrypto >=1.5.1
Requires-Dist: lxml ==5.3.0
Requires-Dist: markdown
Requires-Dist: matplotlib
Requires-Dist: msal ~=1.30.0
Requires-Dist: nessus-file-reader
Requires-Dist: numpy >=1.24.0
Requires-Dist: openpyxl
Requires-Dist: packaging ~=25.0.0
Requires-Dist: pandas
Requires-Dist: pathlib ~=1.0.1
Requires-Dist: pdfplumber ==0.7.6
Requires-Dist: polars >=0.20.0
Requires-Dist: pre-commit
Requires-Dist: psutil ~=6.1.0
Requires-Dist: pyTenable >=1.6.3
Requires-Dist: pyarrow >=14.0.0
Requires-Dist: pydantic ~=2.11.0
Requires-Dist: pypandoc
Requires-Dist: pypandoc-binary
Requires-Dist: pytest
Requires-Dist: python-dateutil ~=2.9.0
Requires-Dist: python-docx
Requires-Dist: python-jwt ==4.1.0
Requires-Dist: rapidfuzz ~=3.7
Requires-Dist: regscale-python-ssp
Requires-Dist: requests >=2.32.0
Requires-Dist: rich ==13.8.0
Requires-Dist: setuptools >=67
Requires-Dist: simple-salesforce
Requires-Dist: smart-open ~=7.0
Requires-Dist: static
Requires-Dist: synqly ==0.4.56
Requires-Dist: tools
Requires-Dist: typing-extensions ~=4.14.1
Requires-Dist: wheel
Requires-Dist: xmltodict
Provides-Extra: airflow
Requires-Dist: MarkupSafe ==2.1.3 ; extra == 'airflow'
Requires-Dist: PyMuPDF >=1.24.7 ; extra == 'airflow'
Requires-Dist: PyYAML ==6.0.1 ; extra == 'airflow'
Requires-Dist: aiohttp ; extra == 'airflow'
Requires-Dist: apache-airflow-providers-common-sql >=1.25.0 ; extra == 'airflow'
Requires-Dist: apache-airflow-providers-postgres ; extra == 'airflow'
Requires-Dist: apache-airflow ==3.1.3 ; extra == 'airflow'
Requires-Dist: asyncpg >=0.29.0 ; extra == 'airflow'
Requires-Dist: beautifulsoup4 ; extra == 'airflow'
Requires-Dist: boto3 ==1.35.10 ; extra == 'airflow'
Requires-Dist: botocore ==1.35.10 ; extra == 'airflow'
Requires-Dist: bs4 ; extra == 'airflow'
Requires-Dist: cacheout ; extra == 'airflow'
Requires-Dist: click ~=8.1.8 ; extra == 'airflow'
Requires-Dist: colorama ==0.4.5 ; extra == 'airflow'
Requires-Dist: crowdstrike-falconpy ==1.4.5 ; extra == 'airflow'
Requires-Dist: cryptography ~=44.0.1 ; extra == 'airflow'
Requires-Dist: distro ==1.8.0 ; extra == 'airflow'
Requires-Dist: docx ==0.2.4 ; extra == 'airflow'
Requires-Dist: filelock ~=3.13.1 ; extra == 'airflow'
Requires-Dist: flask-appbuilder >=4.0.0 ; extra == 'airflow'
Requires-Dist: flask >=2.3.2 ; extra == 'airflow'
Requires-Dist: frontend ; extra == 'airflow'
Requires-Dist: google-api-python-client ; extra == 'airflow'
Requires-Dist: google-cloud-asset ~=3.22 ; extra == 'airflow'
Requires-Dist: google-cloud-securitycenter ~=1.25 ; extra == 'airflow'
Requires-Dist: gql ~=3.5.0 ; extra == 'airflow'
Requires-Dist: greenlet >=3.0.3 ; extra == 'airflow'
Requires-Dist: importlib-metadata >=6.5 ; extra == 'airflow'
Requires-Dist: inflect ; extra == 'airflow'
Requires-Dist: jinja2 >=3.1.5 ; extra == 'airflow'
Requires-Dist: jira >=3.8.0 ; extra == 'airflow'
Requires-Dist: jmespath ==1.0.0 ; extra == 'airflow'
Requires-Dist: jwcrypto >=1.5.1 ; extra == 'airflow'
Requires-Dist: lxml ==5.3.0 ; extra == 'airflow'
Requires-Dist: markdown ; extra == 'airflow'
Requires-Dist: matplotlib ; extra == 'airflow'
Requires-Dist: methodtools ==0.4.7 ; extra == 'airflow'
Requires-Dist: more-itertools ==10.7.0 ; extra == 'airflow'
Requires-Dist: msal ~=1.30.0 ; extra == 'airflow'
Requires-Dist: msgspec ==0.19.0 ; extra == 'airflow'
Requires-Dist: multidict >=6.1.0 ; extra == 'airflow'
Requires-Dist: nessus-file-reader ; extra == 'airflow'
Requires-Dist: networkx ==3.0.0 ; extra == 'airflow'
Requires-Dist: numpy >=1.24.0 ; extra == 'airflow'
Requires-Dist: openpyxl ; extra == 'airflow'
Requires-Dist: opentelemetry-api >=1.24.0 ; extra == 'airflow'
Requires-Dist: opentelemetry-exporter-otlp >=1.24.0 ; extra == 'airflow'
Requires-Dist: opentelemetry-sdk >=1.24.0 ; extra == 'airflow'
Requires-Dist: packaging ~=25.0.0 ; extra == 'airflow'
Requires-Dist: pandas ; extra == 'airflow'
Requires-Dist: pathlib ~=1.0.1 ; extra == 'airflow'
Requires-Dist: pdfplumber ==0.7.6 ; extra == 'airflow'
Requires-Dist: polars >=0.20.0 ; extra == 'airflow'
Requires-Dist: pre-commit ; extra == 'airflow'
Requires-Dist: protobuf ~=4.25.8 ; extra == 'airflow'
Requires-Dist: psutil ~=6.1.0 ; extra == 'airflow'
Requires-Dist: psycopg2-binary ; extra == 'airflow'
Requires-Dist: pyTenable >=1.6.3 ; extra == 'airflow'
Requires-Dist: pyarrow >=14.0.0 ; extra == 'airflow'
Requires-Dist: pydantic ~=2.11.0 ; extra == 'airflow'
Requires-Dist: pypandoc ; extra == 'airflow'
Requires-Dist: pypandoc-binary ; extra == 'airflow'
Requires-Dist: pytest ; extra == 'airflow'
Requires-Dist: python-dateutil ~=2.9.0 ; extra == 'airflow'
Requires-Dist: python-docx ; extra == 'airflow'
Requires-Dist: python-jwt ==4.1.0 ; extra == 'airflow'
Requires-Dist: rapidfuzz ~=3.7 ; extra == 'airflow'
Requires-Dist: regscale-python-ssp ; extra == 'airflow'
Requires-Dist: requests >=2.32.0 ; extra == 'airflow'
Requires-Dist: rich ==13.8.0 ; extra == 'airflow'
Requires-Dist: setuptools >=67 ; extra == 'airflow'
Requires-Dist: simple-salesforce ; extra == 'airflow'
Requires-Dist: smart-open ~=7.0 ; extra == 'airflow'
Requires-Dist: static ; extra == 'airflow'
Requires-Dist: synqly ==0.4.56 ; extra == 'airflow'
Requires-Dist: tools ; extra == 'airflow'
Requires-Dist: typing-extensions ~=4.14.1 ; extra == 'airflow'
Requires-Dist: wheel ; extra == 'airflow'
Requires-Dist: xmltodict ; extra == 'airflow'
Provides-Extra: airflow-azure
Requires-Dist: MarkupSafe ==2.1.3 ; extra == 'airflow-azure'
Requires-Dist: PyMuPDF >=1.24.7 ; extra == 'airflow-azure'
Requires-Dist: PyYAML ==6.0.1 ; extra == 'airflow-azure'
Requires-Dist: aiohttp ; extra == 'airflow-azure'
Requires-Dist: apache-airflow-providers-common-sql >=1.25.0 ; extra == 'airflow-azure'
Requires-Dist: apache-airflow-providers-microsoft-azure ; extra == 'airflow-azure'
Requires-Dist: apache-airflow-providers-postgres ; extra == 'airflow-azure'
Requires-Dist: apache-airflow ==3.1.3 ; extra == 'airflow-azure'
Requires-Dist: asyncpg >=0.29.0 ; extra == 'airflow-azure'
Requires-Dist: azure-storage-blob ; extra == 'airflow-azure'
Requires-Dist: beautifulsoup4 ; extra == 'airflow-azure'
Requires-Dist: boto3 ==1.35.10 ; extra == 'airflow-azure'
Requires-Dist: botocore ==1.35.10 ; extra == 'airflow-azure'
Requires-Dist: bs4 ; extra == 'airflow-azure'
Requires-Dist: cacheout ; extra == 'airflow-azure'
Requires-Dist: click ~=8.1.8 ; extra == 'airflow-azure'
Requires-Dist: colorama ==0.4.5 ; extra == 'airflow-azure'
Requires-Dist: crowdstrike-falconpy ==1.4.5 ; extra == 'airflow-azure'
Requires-Dist: cryptography ~=44.0.1 ; extra == 'airflow-azure'
Requires-Dist: distro ==1.8.0 ; extra == 'airflow-azure'
Requires-Dist: docx ==0.2.4 ; extra == 'airflow-azure'
Requires-Dist: filelock ~=3.13.1 ; extra == 'airflow-azure'
Requires-Dist: flask-appbuilder >=4.0.0 ; extra == 'airflow-azure'
Requires-Dist: flask >=2.3.2 ; extra == 'airflow-azure'
Requires-Dist: frontend ; extra == 'airflow-azure'
Requires-Dist: google-api-python-client ; extra == 'airflow-azure'
Requires-Dist: google-cloud-asset ~=3.22 ; extra == 'airflow-azure'
Requires-Dist: google-cloud-securitycenter ~=1.25 ; extra == 'airflow-azure'
Requires-Dist: gql ~=3.5.0 ; extra == 'airflow-azure'
Requires-Dist: greenlet >=3.0.3 ; extra == 'airflow-azure'
Requires-Dist: importlib-metadata >=6.5 ; extra == 'airflow-azure'
Requires-Dist: inflect ; extra == 'airflow-azure'
Requires-Dist: jinja2 >=3.1.5 ; extra == 'airflow-azure'
Requires-Dist: jira >=3.8.0 ; extra == 'airflow-azure'
Requires-Dist: jmespath ==1.0.0 ; extra == 'airflow-azure'
Requires-Dist: jwcrypto >=1.5.1 ; extra == 'airflow-azure'
Requires-Dist: lxml ==5.3.0 ; extra == 'airflow-azure'
Requires-Dist: markdown ; extra == 'airflow-azure'
Requires-Dist: matplotlib ; extra == 'airflow-azure'
Requires-Dist: methodtools ==0.4.7 ; extra == 'airflow-azure'
Requires-Dist: more-itertools ==10.7.0 ; extra == 'airflow-azure'
Requires-Dist: msal ~=1.30.0 ; extra == 'airflow-azure'
Requires-Dist: msgspec ==0.19.0 ; extra == 'airflow-azure'
Requires-Dist: multidict >=6.1.0 ; extra == 'airflow-azure'
Requires-Dist: nessus-file-reader ; extra == 'airflow-azure'
Requires-Dist: networkx ==3.0.0 ; extra == 'airflow-azure'
Requires-Dist: numpy >=1.24.0 ; extra == 'airflow-azure'
Requires-Dist: openpyxl ; extra == 'airflow-azure'
Requires-Dist: opentelemetry-api >=1.24.0 ; extra == 'airflow-azure'
Requires-Dist: opentelemetry-exporter-otlp >=1.24.0 ; extra == 'airflow-azure'
Requires-Dist: opentelemetry-sdk >=1.24.0 ; extra == 'airflow-azure'
Requires-Dist: packaging ~=25.0.0 ; extra == 'airflow-azure'
Requires-Dist: pandas ; extra == 'airflow-azure'
Requires-Dist: pathlib ~=1.0.1 ; extra == 'airflow-azure'
Requires-Dist: pdfplumber ==0.7.6 ; extra == 'airflow-azure'
Requires-Dist: pendulum >=2.1.2 ; extra == 'airflow-azure'
Requires-Dist: polars >=0.20.0 ; extra == 'airflow-azure'
Requires-Dist: pre-commit ; extra == 'airflow-azure'
Requires-Dist: protobuf ~=4.25.8 ; extra == 'airflow-azure'
Requires-Dist: psutil ~=6.1.0 ; extra == 'airflow-azure'
Requires-Dist: psycopg2-binary ; extra == 'airflow-azure'
Requires-Dist: pyTenable >=1.6.3 ; extra == 'airflow-azure'
Requires-Dist: pyarrow >=14.0.0 ; extra == 'airflow-azure'
Requires-Dist: pydantic ~=2.11.0 ; extra == 'airflow-azure'
Requires-Dist: pypandoc ; extra == 'airflow-azure'
Requires-Dist: pypandoc-binary ; extra == 'airflow-azure'
Requires-Dist: pytest ; extra == 'airflow-azure'
Requires-Dist: python-dateutil ~=2.9.0 ; extra == 'airflow-azure'
Requires-Dist: python-docx ; extra == 'airflow-azure'
Requires-Dist: python-jwt ==4.1.0 ; extra == 'airflow-azure'
Requires-Dist: rapidfuzz ~=3.7 ; extra == 'airflow-azure'
Requires-Dist: regscale-python-ssp ; extra == 'airflow-azure'
Requires-Dist: requests >=2.32.0 ; extra == 'airflow-azure'
Requires-Dist: rich ==13.8.0 ; extra == 'airflow-azure'
Requires-Dist: setuptools >=67 ; extra == 'airflow-azure'
Requires-Dist: simple-salesforce ; extra == 'airflow-azure'
Requires-Dist: smart-open ~=7.0 ; extra == 'airflow-azure'
Requires-Dist: static ; extra == 'airflow-azure'
Requires-Dist: synqly ==0.4.56 ; extra == 'airflow-azure'
Requires-Dist: tools ; extra == 'airflow-azure'
Requires-Dist: typing-extensions ~=4.14.1 ; extra == 'airflow-azure'
Requires-Dist: wheel ; extra == 'airflow-azure'
Requires-Dist: xmltodict ; extra == 'airflow-azure'
Provides-Extra: airflow-sqlserver
Requires-Dist: MarkupSafe ==2.1.3 ; extra == 'airflow-sqlserver'
Requires-Dist: PyMuPDF >=1.24.7 ; extra == 'airflow-sqlserver'
Requires-Dist: PyYAML ==6.0.1 ; extra == 'airflow-sqlserver'
Requires-Dist: aiohttp ; extra == 'airflow-sqlserver'
Requires-Dist: apache-airflow-providers-common-sql >=1.25.0 ; extra == 'airflow-sqlserver'
Requires-Dist: apache-airflow-providers-microsoft-mssql ; extra == 'airflow-sqlserver'
Requires-Dist: apache-airflow-providers-postgres ; extra == 'airflow-sqlserver'
Requires-Dist: apache-airflow ==3.1.3 ; extra == 'airflow-sqlserver'
Requires-Dist: asyncpg >=0.29.0 ; extra == 'airflow-sqlserver'
Requires-Dist: beautifulsoup4 ; extra == 'airflow-sqlserver'
Requires-Dist: boto3 ==1.35.10 ; extra == 'airflow-sqlserver'
Requires-Dist: botocore ==1.35.10 ; extra == 'airflow-sqlserver'
Requires-Dist: bs4 ; extra == 'airflow-sqlserver'
Requires-Dist: cacheout ; extra == 'airflow-sqlserver'
Requires-Dist: click ~=8.1.8 ; extra == 'airflow-sqlserver'
Requires-Dist: colorama ==0.4.5 ; extra == 'airflow-sqlserver'
Requires-Dist: crowdstrike-falconpy ==1.4.5 ; extra == 'airflow-sqlserver'
Requires-Dist: cryptography ~=44.0.1 ; extra == 'airflow-sqlserver'
Requires-Dist: distro ==1.8.0 ; extra == 'airflow-sqlserver'
Requires-Dist: docx ==0.2.4 ; extra == 'airflow-sqlserver'
Requires-Dist: filelock ~=3.13.1 ; extra == 'airflow-sqlserver'
Requires-Dist: flask-appbuilder >=4.0.0 ; extra == 'airflow-sqlserver'
Requires-Dist: flask >=2.3.2 ; extra == 'airflow-sqlserver'
Requires-Dist: frontend ; extra == 'airflow-sqlserver'
Requires-Dist: google-api-python-client ; extra == 'airflow-sqlserver'
Requires-Dist: google-cloud-asset ~=3.22 ; extra == 'airflow-sqlserver'
Requires-Dist: google-cloud-securitycenter ~=1.25 ; extra == 'airflow-sqlserver'
Requires-Dist: gql ~=3.5.0 ; extra == 'airflow-sqlserver'
Requires-Dist: greenlet >=3.0.3 ; extra == 'airflow-sqlserver'
Requires-Dist: importlib-metadata >=6.5 ; extra == 'airflow-sqlserver'
Requires-Dist: inflect ; extra == 'airflow-sqlserver'
Requires-Dist: jinja2 >=3.1.5 ; extra == 'airflow-sqlserver'
Requires-Dist: jira >=3.8.0 ; extra == 'airflow-sqlserver'
Requires-Dist: jmespath ==1.0.0 ; extra == 'airflow-sqlserver'
Requires-Dist: jwcrypto >=1.5.1 ; extra == 'airflow-sqlserver'
Requires-Dist: lxml ==5.3.0 ; extra == 'airflow-sqlserver'
Requires-Dist: markdown ; extra == 'airflow-sqlserver'
Requires-Dist: matplotlib ; extra == 'airflow-sqlserver'
Requires-Dist: methodtools ==0.4.7 ; extra == 'airflow-sqlserver'
Requires-Dist: more-itertools ==10.7.0 ; extra == 'airflow-sqlserver'
Requires-Dist: msal ~=1.30.0 ; extra == 'airflow-sqlserver'
Requires-Dist: msgspec ==0.19.0 ; extra == 'airflow-sqlserver'
Requires-Dist: multidict >=6.1.0 ; extra == 'airflow-sqlserver'
Requires-Dist: nessus-file-reader ; extra == 'airflow-sqlserver'
Requires-Dist: networkx ==3.0.0 ; extra == 'airflow-sqlserver'
Requires-Dist: numpy >=1.24.0 ; extra == 'airflow-sqlserver'
Requires-Dist: openpyxl ; extra == 'airflow-sqlserver'
Requires-Dist: opentelemetry-api >=1.24.0 ; extra == 'airflow-sqlserver'
Requires-Dist: opentelemetry-exporter-otlp >=1.24.0 ; extra == 'airflow-sqlserver'
Requires-Dist: opentelemetry-sdk >=1.24.0 ; extra == 'airflow-sqlserver'
Requires-Dist: packaging ~=25.0.0 ; extra == 'airflow-sqlserver'
Requires-Dist: pandas ; extra == 'airflow-sqlserver'
Requires-Dist: pathlib ~=1.0.1 ; extra == 'airflow-sqlserver'
Requires-Dist: pdfplumber ==0.7.6 ; extra == 'airflow-sqlserver'
Requires-Dist: polars >=0.20.0 ; extra == 'airflow-sqlserver'
Requires-Dist: pre-commit ; extra == 'airflow-sqlserver'
Requires-Dist: protobuf ~=4.25.8 ; extra == 'airflow-sqlserver'
Requires-Dist: psutil ~=6.1.0 ; extra == 'airflow-sqlserver'
Requires-Dist: psycopg2-binary ; extra == 'airflow-sqlserver'
Requires-Dist: pyTenable >=1.6.3 ; extra == 'airflow-sqlserver'
Requires-Dist: pyarrow >=14.0.0 ; extra == 'airflow-sqlserver'
Requires-Dist: pydantic ~=2.11.0 ; extra == 'airflow-sqlserver'
Requires-Dist: pymssql ; extra == 'airflow-sqlserver'
Requires-Dist: pyodbc ; extra == 'airflow-sqlserver'
Requires-Dist: pypandoc ; extra == 'airflow-sqlserver'
Requires-Dist: pypandoc-binary ; extra == 'airflow-sqlserver'
Requires-Dist: pytest ; extra == 'airflow-sqlserver'
Requires-Dist: python-dateutil ~=2.9.0 ; extra == 'airflow-sqlserver'
Requires-Dist: python-docx ; extra == 'airflow-sqlserver'
Requires-Dist: python-jwt ==4.1.0 ; extra == 'airflow-sqlserver'
Requires-Dist: rapidfuzz ~=3.7 ; extra == 'airflow-sqlserver'
Requires-Dist: regscale-python-ssp ; extra == 'airflow-sqlserver'
Requires-Dist: requests >=2.32.0 ; extra == 'airflow-sqlserver'
Requires-Dist: rich ==13.8.0 ; extra == 'airflow-sqlserver'
Requires-Dist: setuptools >=67 ; extra == 'airflow-sqlserver'
Requires-Dist: simple-salesforce ; extra == 'airflow-sqlserver'
Requires-Dist: smart-open ~=7.0 ; extra == 'airflow-sqlserver'
Requires-Dist: static ; extra == 'airflow-sqlserver'
Requires-Dist: synqly ==0.4.56 ; extra == 'airflow-sqlserver'
Requires-Dist: tools ; extra == 'airflow-sqlserver'
Requires-Dist: typing-extensions ~=4.14.1 ; extra == 'airflow-sqlserver'
Requires-Dist: wheel ; extra == 'airflow-sqlserver'
Requires-Dist: xmltodict ; extra == 'airflow-sqlserver'
Provides-Extra: all
Requires-Dist: MarkupSafe ==2.1.3 ; extra == 'all'
Requires-Dist: PyMuPDF >=1.24.7 ; extra == 'all'
Requires-Dist: PyYAML ==6.0.1 ; extra == 'all'
Requires-Dist: aiohttp ; extra == 'all'
Requires-Dist: ansible ; extra == 'all'
Requires-Dist: apache-airflow-providers-common-sql >=1.25.0 ; extra == 'all'
Requires-Dist: apache-airflow-providers-postgres ; extra == 'all'
Requires-Dist: apache-airflow ==3.1.3 ; extra == 'all'
Requires-Dist: asyncpg >=0.29.0 ; extra == 'all'
Requires-Dist: beautifulsoup4 ; extra == 'all'
Requires-Dist: boto3 ==1.35.10 ; extra == 'all'
Requires-Dist: botocore ==1.35.10 ; extra == 'all'
Requires-Dist: bs4 ; extra == 'all'
Requires-Dist: cacheout ; extra == 'all'
Requires-Dist: click ~=8.1.8 ; extra == 'all'
Requires-Dist: colorama ==0.4.5 ; extra == 'all'
Requires-Dist: crowdstrike-falconpy ==1.4.5 ; extra == 'all'
Requires-Dist: cryptography ~=44.0.1 ; extra == 'all'
Requires-Dist: distro ==1.8.0 ; extra == 'all'
Requires-Dist: docx ==0.2.4 ; extra == 'all'
Requires-Dist: filelock ~=3.13.1 ; extra == 'all'
Requires-Dist: flask ; extra == 'all'
Requires-Dist: flask-apispec ; extra == 'all'
Requires-Dist: flask-appbuilder ; extra == 'all'
Requires-Dist: flask-appbuilder >=4.0.0 ; extra == 'all'
Requires-Dist: flask-rebar ; extra == 'all'
Requires-Dist: flask-restx ; extra == 'all'
Requires-Dist: flask >=2.3.2 ; extra == 'all'
Requires-Dist: frontend ; extra == 'all'
Requires-Dist: google-api-python-client ; extra == 'all'
Requires-Dist: google-cloud-asset ~=3.22 ; extra == 'all'
Requires-Dist: google-cloud-securitycenter ~=1.25 ; extra == 'all'
Requires-Dist: gql ~=3.5.0 ; extra == 'all'
Requires-Dist: greenlet >=3.0.3 ; extra == 'all'
Requires-Dist: importlib-metadata >=6.5 ; extra == 'all'
Requires-Dist: importlib-resources ; extra == 'all'
Requires-Dist: inflect ; extra == 'all'
Requires-Dist: jinja2 ; extra == 'all'
Requires-Dist: jinja2 >=3.1.5 ; extra == 'all'
Requires-Dist: jira >=3.8.0 ; extra == 'all'
Requires-Dist: jmespath ==1.0.0 ; extra == 'all'
Requires-Dist: jwcrypto >=1.5.1 ; extra == 'all'
Requires-Dist: lxml ==5.3.0 ; extra == 'all'
Requires-Dist: markdown ; extra == 'all'
Requires-Dist: matplotlib ; extra == 'all'
Requires-Dist: methodtools ==0.4.7 ; extra == 'all'
Requires-Dist: more-itertools ==10.7.0 ; extra == 'all'
Requires-Dist: msal ~=1.30.0 ; extra == 'all'
Requires-Dist: msgspec ==0.19.0 ; extra == 'all'
Requires-Dist: multidict >=6.1.0 ; extra == 'all'
Requires-Dist: nessus-file-reader ; extra == 'all'
Requires-Dist: networkx ==3.0.0 ; extra == 'all'
Requires-Dist: numpy >=1.24.0 ; extra == 'all'
Requires-Dist: openpyxl ; extra == 'all'
Requires-Dist: opentelemetry-api >=1.24.0 ; extra == 'all'
Requires-Dist: opentelemetry-exporter-otlp >=1.24.0 ; extra == 'all'
Requires-Dist: opentelemetry-sdk >=1.24.0 ; extra == 'all'
Requires-Dist: packaging ~=25.0.0 ; extra == 'all'
Requires-Dist: pandas ; extra == 'all'
Requires-Dist: pathlib ~=1.0.1 ; extra == 'all'
Requires-Dist: pdfplumber ==0.7.6 ; extra == 'all'
Requires-Dist: polars >=0.20.0 ; extra == 'all'
Requires-Dist: pre-commit ; extra == 'all'
Requires-Dist: protobuf ~=4.25.8 ; extra == 'all'
Requires-Dist: psutil ~=6.1.0 ; extra == 'all'
Requires-Dist: psycopg2-binary ; extra == 'all'
Requires-Dist: pyTenable >=1.6.3 ; extra == 'all'
Requires-Dist: pyarrow >=14.0.0 ; extra == 'all'
Requires-Dist: pydantic ~=2.11.0 ; extra == 'all'
Requires-Dist: pypandoc ; extra == 'all'
Requires-Dist: pypandoc-binary ; extra == 'all'
Requires-Dist: pytest ; extra == 'all'
Requires-Dist: python-dateutil ~=2.9.0 ; extra == 'all'
Requires-Dist: python-docx ; extra == 'all'
Requires-Dist: python-jwt ==4.1.0 ; extra == 'all'
Requires-Dist: rapidfuzz ~=3.7 ; extra == 'all'
Requires-Dist: regscale-python-ssp ; extra == 'all'
Requires-Dist: requests >=2.32.0 ; extra == 'all'
Requires-Dist: rich ==13.8.0 ; extra == 'all'
Requires-Dist: setuptools >=67 ; extra == 'all'
Requires-Dist: simple-salesforce ; extra == 'all'
Requires-Dist: smart-open ~=7.0 ; extra == 'all'
Requires-Dist: static ; extra == 'all'
Requires-Dist: synqly ==0.4.56 ; extra == 'all'
Requires-Dist: tools ; extra == 'all'
Requires-Dist: typing-extensions ~=4.14.1 ; extra == 'all'
Requires-Dist: werkzeug >=2.3.8 ; extra == 'all'
Requires-Dist: wheel ; extra == 'all'
Requires-Dist: xmltodict ; extra == 'all'
Provides-Extra: ansible
Requires-Dist: PyMuPDF >=1.24.7 ; extra == 'ansible'
Requires-Dist: PyYAML ==6.0.1 ; extra == 'ansible'
Requires-Dist: aiohttp ; extra == 'ansible'
Requires-Dist: ansible ; extra == 'ansible'
Requires-Dist: beautifulsoup4 ; extra == 'ansible'
Requires-Dist: boto3 ==1.35.10 ; extra == 'ansible'
Requires-Dist: botocore ==1.35.10 ; extra == 'ansible'
Requires-Dist: bs4 ; extra == 'ansible'
Requires-Dist: cacheout ; extra == 'ansible'
Requires-Dist: click ~=8.1.8 ; extra == 'ansible'
Requires-Dist: colorama ==0.4.5 ; extra == 'ansible'
Requires-Dist: crowdstrike-falconpy ==1.4.5 ; extra == 'ansible'
Requires-Dist: cryptography ~=44.0.1 ; extra == 'ansible'
Requires-Dist: distro ==1.8.0 ; extra == 'ansible'
Requires-Dist: docx ==0.2.4 ; extra == 'ansible'
Requires-Dist: filelock ~=3.13.1 ; extra == 'ansible'
Requires-Dist: frontend ; extra == 'ansible'
Requires-Dist: google-api-python-client ; extra == 'ansible'
Requires-Dist: google-cloud-asset ~=3.22 ; extra == 'ansible'
Requires-Dist: google-cloud-securitycenter ~=1.25 ; extra == 'ansible'
Requires-Dist: gql ~=3.5.0 ; extra == 'ansible'
Requires-Dist: inflect ; extra == 'ansible'
Requires-Dist: jinja2 ; extra == 'ansible'
Requires-Dist: jira >=3.8.0 ; extra == 'ansible'
Requires-Dist: jwcrypto >=1.5.1 ; extra == 'ansible'
Requires-Dist: lxml ==5.3.0 ; extra == 'ansible'
Requires-Dist: markdown ; extra == 'ansible'
Requires-Dist: matplotlib ; extra == 'ansible'
Requires-Dist: msal ~=1.30.0 ; extra == 'ansible'
Requires-Dist: nessus-file-reader ; extra == 'ansible'
Requires-Dist: numpy >=1.24.0 ; extra == 'ansible'
Requires-Dist: openpyxl ; extra == 'ansible'
Requires-Dist: packaging ~=25.0.0 ; extra == 'ansible'
Requires-Dist: pandas ; extra == 'ansible'
Requires-Dist: pathlib ~=1.0.1 ; extra == 'ansible'
Requires-Dist: pdfplumber ==0.7.6 ; extra == 'ansible'
Requires-Dist: polars >=0.20.0 ; extra == 'ansible'
Requires-Dist: pre-commit ; extra == 'ansible'
Requires-Dist: psutil ~=6.1.0 ; extra == 'ansible'
Requires-Dist: pyTenable >=1.6.3 ; extra == 'ansible'
Requires-Dist: pyarrow >=14.0.0 ; extra == 'ansible'
Requires-Dist: pydantic ~=2.11.0 ; extra == 'ansible'
Requires-Dist: pypandoc ; extra == 'ansible'
Requires-Dist: pypandoc-binary ; extra == 'ansible'
Requires-Dist: pytest ; extra == 'ansible'
Requires-Dist: python-dateutil ~=2.9.0 ; extra == 'ansible'
Requires-Dist: python-docx ; extra == 'ansible'
Requires-Dist: python-jwt ==4.1.0 ; extra == 'ansible'
Requires-Dist: rapidfuzz ~=3.7 ; extra == 'ansible'
Requires-Dist: regscale-python-ssp ; extra == 'ansible'
Requires-Dist: requests >=2.32.0 ; extra == 'ansible'
Requires-Dist: rich ==13.8.0 ; extra == 'ansible'
Requires-Dist: setuptools >=67 ; extra == 'ansible'
Requires-Dist: simple-salesforce ; extra == 'ansible'
Requires-Dist: smart-open ~=7.0 ; extra == 'ansible'
Requires-Dist: static ; extra == 'ansible'
Requires-Dist: synqly ==0.4.56 ; extra == 'ansible'
Requires-Dist: tools ; extra == 'ansible'
Requires-Dist: typing-extensions ~=4.14.1 ; extra == 'ansible'
Requires-Dist: wheel ; extra == 'ansible'
Requires-Dist: xmltodict ; extra == 'ansible'
Provides-Extra: dev
Requires-Dist: GitPython ; extra == 'dev'
Requires-Dist: PyMuPDF >=1.24.7 ; extra == 'dev'
Requires-Dist: PyYAML ==6.0.1 ; extra == 'dev'
Requires-Dist: aiohttp ; extra == 'dev'
Requires-Dist: beautifulsoup4 ; extra == 'dev'
Requires-Dist: black ; extra == 'dev'
Requires-Dist: boto3 ==1.35.10 ; extra == 'dev'
Requires-Dist: botocore ==1.35.10 ; extra == 'dev'
Requires-Dist: bs4 ; extra == 'dev'
Requires-Dist: cacheout ; extra == 'dev'
Requires-Dist: click ~=8.1.8 ; extra == 'dev'
Requires-Dist: colorama ==0.4.5 ; extra == 'dev'
Requires-Dist: coveralls ; extra == 'dev'
Requires-Dist: crowdstrike-falconpy ==1.4.5 ; extra == 'dev'
Requires-Dist: cryptography ~=44.0.1 ; extra == 'dev'
Requires-Dist: darglint ; extra == 'dev'
Requires-Dist: distro ==1.8.0 ; extra == 'dev'
Requires-Dist: docx ==0.2.4 ; extra == 'dev'
Requires-Dist: filelock ~=3.13.1 ; extra == 'dev'
Requires-Dist: flake8 ; extra == 'dev'
Requires-Dist: freezegun ; extra == 'dev'
Requires-Dist: frontend ; extra == 'dev'
Requires-Dist: google-api-python-client ; extra == 'dev'
Requires-Dist: google-cloud-asset ~=3.22 ; extra == 'dev'
Requires-Dist: google-cloud-securitycenter ~=1.25 ; extra == 'dev'
Requires-Dist: gql ~=3.5.0 ; extra == 'dev'
Requires-Dist: inflect ; extra == 'dev'
Requires-Dist: isort ; extra == 'dev'
Requires-Dist: jira >=3.8.0 ; extra == 'dev'
Requires-Dist: jwcrypto >=1.5.1 ; extra == 'dev'
Requires-Dist: lxml-stubs ; extra == 'dev'
Requires-Dist: lxml ==5.3.0 ; extra == 'dev'
Requires-Dist: markdown ; extra == 'dev'
Requires-Dist: matplotlib ; extra == 'dev'
Requires-Dist: moto ; extra == 'dev'
Requires-Dist: msal ~=1.30.0 ; extra == 'dev'
Requires-Dist: mypy ; extra == 'dev'
Requires-Dist: nessus-file-reader ; extra == 'dev'
Requires-Dist: numpy >=1.24.0 ; extra == 'dev'
Requires-Dist: openpyxl ; extra == 'dev'
Requires-Dist: packaging ~=25.0.0 ; extra == 'dev'
Requires-Dist: pandas ; extra == 'dev'
Requires-Dist: pandas-stubs ; extra == 'dev'
Requires-Dist: pathlib ~=1.0.1 ; extra == 'dev'
Requires-Dist: pdfplumber ==0.7.6 ; extra == 'dev'
Requires-Dist: pipenv ; extra == 'dev'
Requires-Dist: polars >=0.20.0 ; extra == 'dev'
Requires-Dist: pre-commit ; extra == 'dev'
Requires-Dist: psutil ~=6.1.0 ; extra == 'dev'
Requires-Dist: pyTenable >=1.6.3 ; extra == 'dev'
Requires-Dist: pyarrow >=14.0.0 ; extra == 'dev'
Requires-Dist: pydantic ~=2.11.0 ; extra == 'dev'
Requires-Dist: pylint ; extra == 'dev'
Requires-Dist: pypandoc ; extra == 'dev'
Requires-Dist: pypandoc-binary ; extra == 'dev'
Requires-Dist: pytest ; extra == 'dev'
Requires-Dist: pytest-asyncio ; extra == 'dev'
Requires-Dist: pytest-cov ; extra == 'dev'
Requires-Dist: pytest-html ; extra == 'dev'
Requires-Dist: pytest-mock ; extra == 'dev'
Requires-Dist: pytest-rerunfailures ; extra == 'dev'
Requires-Dist: pytest-timeout ; extra == 'dev'
Requires-Dist: pytest-xdist ; extra == 'dev'
Requires-Dist: pytest >=5 ; extra == 'dev'
Requires-Dist: python-dateutil ~=2.9.0 ; extra == 'dev'
Requires-Dist: python-docx ; extra == 'dev'
Requires-Dist: python-jwt ==4.1.0 ; extra == 'dev'
Requires-Dist: radon ; extra == 'dev'
Requires-Dist: rapidfuzz ~=3.7 ; extra == 'dev'
Requires-Dist: regscale-python-ssp ; extra == 'dev'
Requires-Dist: requests >=2.32.0 ; extra == 'dev'
Requires-Dist: rich ==13.8.0 ; extra == 'dev'
Requires-Dist: setuptools >=67 ; extra == 'dev'
Requires-Dist: simple-salesforce ; extra == 'dev'
Requires-Dist: smart-open ~=7.0 ; extra == 'dev'
Requires-Dist: sphinx ; extra == 'dev'
Requires-Dist: sphinx-autodoc-typehints ; extra == 'dev'
Requires-Dist: sphinx-click ; extra == 'dev'
Requires-Dist: static ; extra == 'dev'
Requires-Dist: synqly ==0.4.56 ; extra == 'dev'
Requires-Dist: tools ; extra == 'dev'
Requires-Dist: types-python-dateutil ; extra == 'dev'
Requires-Dist: types-pyyaml ; extra == 'dev'
Requires-Dist: types-requests ; extra == 'dev'
Requires-Dist: typing-extensions ~=4.14.1 ; extra == 'dev'
Requires-Dist: watchdog ; extra == 'dev'
Requires-Dist: wheel ; extra == 'dev'
Requires-Dist: xmltodict ; extra == 'dev'
Provides-Extra: server
Requires-Dist: PyMuPDF >=1.24.7 ; extra == 'server'
Requires-Dist: PyYAML ==6.0.1 ; extra == 'server'
Requires-Dist: aiohttp ; extra == 'server'
Requires-Dist: beautifulsoup4 ; extra == 'server'
Requires-Dist: boto3 ==1.35.10 ; extra == 'server'
Requires-Dist: botocore ==1.35.10 ; extra == 'server'
Requires-Dist: bs4 ; extra == 'server'
Requires-Dist: cacheout ; extra == 'server'
Requires-Dist: click ~=8.1.8 ; extra == 'server'
Requires-Dist: colorama ==0.4.5 ; extra == 'server'
Requires-Dist: crowdstrike-falconpy ==1.4.5 ; extra == 'server'
Requires-Dist: cryptography ~=44.0.1 ; extra == 'server'
Requires-Dist: distro ==1.8.0 ; extra == 'server'
Requires-Dist: docx ==0.2.4 ; extra == 'server'
Requires-Dist: filelock ~=3.13.1 ; extra == 'server'
Requires-Dist: flask ; extra == 'server'
Requires-Dist: flask-apispec ; extra == 'server'
Requires-Dist: flask-appbuilder ; extra == 'server'
Requires-Dist: flask-rebar ; extra == 'server'
Requires-Dist: flask-restx ; extra == 'server'
Requires-Dist: frontend ; extra == 'server'
Requires-Dist: google-api-python-client ; extra == 'server'
Requires-Dist: google-cloud-asset ~=3.22 ; extra == 'server'
Requires-Dist: google-cloud-securitycenter ~=1.25 ; extra == 'server'
Requires-Dist: gql ~=3.5.0 ; extra == 'server'
Requires-Dist: importlib-resources ; extra == 'server'
Requires-Dist: inflect ; extra == 'server'
Requires-Dist: jira >=3.8.0 ; extra == 'server'
Requires-Dist: jwcrypto >=1.5.1 ; extra == 'server'
Requires-Dist: lxml ==5.3.0 ; extra == 'server'
Requires-Dist: markdown ; extra == 'server'
Requires-Dist: matplotlib ; extra == 'server'
Requires-Dist: msal ~=1.30.0 ; extra == 'server'
Requires-Dist: nessus-file-reader ; extra == 'server'
Requires-Dist: numpy >=1.24.0 ; extra == 'server'
Requires-Dist: openpyxl ; extra == 'server'
Requires-Dist: packaging ~=25.0.0 ; extra == 'server'
Requires-Dist: pandas ; extra == 'server'
Requires-Dist: pathlib ~=1.0.1 ; extra == 'server'
Requires-Dist: pdfplumber ==0.7.6 ; extra == 'server'
Requires-Dist: polars >=0.20.0 ; extra == 'server'
Requires-Dist: pre-commit ; extra == 'server'
Requires-Dist: psutil ~=6.1.0 ; extra == 'server'
Requires-Dist: pyTenable >=1.6.3 ; extra == 'server'
Requires-Dist: pyarrow >=14.0.0 ; extra == 'server'
Requires-Dist: pydantic ~=2.11.0 ; extra == 'server'
Requires-Dist: pypandoc ; extra == 'server'
Requires-Dist: pypandoc-binary ; extra == 'server'
Requires-Dist: pytest ; extra == 'server'
Requires-Dist: python-dateutil ~=2.9.0 ; extra == 'server'
Requires-Dist: python-docx ; extra == 'server'
Requires-Dist: python-jwt ==4.1.0 ; extra == 'server'
Requires-Dist: rapidfuzz ~=3.7 ; extra == 'server'
Requires-Dist: regscale-python-ssp ; extra == 'server'
Requires-Dist: requests >=2.32.0 ; extra == 'server'
Requires-Dist: rich ==13.8.0 ; extra == 'server'
Requires-Dist: setuptools >=67 ; extra == 'server'
Requires-Dist: simple-salesforce ; extra == 'server'
Requires-Dist: smart-open ~=7.0 ; extra == 'server'
Requires-Dist: static ; extra == 'server'
Requires-Dist: synqly ==0.4.56 ; extra == 'server'
Requires-Dist: tools ; extra == 'server'
Requires-Dist: typing-extensions ~=4.14.1 ; extra == 'server'
Requires-Dist: werkzeug >=2.3.8 ; extra == 'server'
Requires-Dist: wheel ; extra == 'server'
Requires-Dist: xmltodict ; extra == 'server'
